toneswiper/__init__.py
toneswiper/io.py
toneswiper/spectogram.py
toneswiper/textbubbles.py
toneswiper/toneswiper.py
toneswiper/ui_helpers.py
toneswiper-0.3.3.dist-info/licenses/LICENSE
toneswiper-0.3.3.dist-info/METADATA
toneswiper-0.3.3.dist-info/WHEEL
toneswiper-0.3.3.dist-info/entry_points.txt
toneswiper-0.3.3.dist-info/top_level.txt
toneswiper-0.3.3.dist-info/RECORD
