Metadata-Version: 2.4
Name: toneswiper
Version: 0.3.3
Summary: A tool for manually annotating audio with ToDI-style prosody.
Author-email: mwestera <m.westera@hum.leidenuniv.nl>
Project-URL: Homepage, https://github.com/mwestera/toneswiper
Project-URL: Bug Tracker, https://github.com/mwestera/toneswiper/issues
Classifier: Programming Language :: Python :: 3
Classifier: Operating System :: OS Independent
Classifier: Development Status :: 3 - Alpha
Classifier: Intended Audience :: Science/Research
Classifier: Topic :: Text Processing :: Linguistic
Requires-Python: >=3.10
License-File: LICENSE
Requires-Dist: pyqt6
Requires-Dist: tgt
Requires-Dist: praat-parselmouth
Requires-Dist: numpy
Requires-Dist: matplotlib
Requires-Dist: soundfile
Requires-Dist: sounddevice
Requires-Dist: pylibrb
Dynamic: license-file
